{"posts":[{"id":"2019/11/27/Movie-supplement-plan-Infernal-Affairs.md","slug":"2019/11/27/movie-supplement-plan-infernal-affairs","body":"\n# 电影补档计划：无间道\n\n![無間道](https://img3.doubanio.com/view/photo/l/public/p2564556863.webp)\n\n陈永仁是被缉毒警察黄志成安排到贩毒集团的卧底，而刘建明则是贩毒集团韩琛安排到警方的卧底。一次执行任务的时候，双方都了解到对方有安插卧底，于是开始安排这两个内鬼互相挖出对方。\n\n没想到韩琛竟然安排杀死了黄志成，刘建明开始想做好人，安排杀死韩琛。陈永仁终于可以不做卧底，找刘建明要身份的时候意识到刘建明就是内鬼，并拿走了证据。\n\n陈永仁约刘建明，用新身份换证据，实际已经联系了警察。下电梯的时候，碰到了贩毒集团的另一个内鬼，陈友仁被杀，刘建明在电梯里杀死内鬼，完全洗白。\n\n无间道这个标题完全是给刘建明的定的，从从安排到警校，刘建明就希望成为一个好人，然而从升迁、调查被安排调查内鬼、黄志成被杀、认识陈永仁再到杀死另一个内鬼，刘建明始终没能成为好人。故事结局，陈永仁被证明清白安葬在黄志成旁边，刘建明依然是警察，以后还要伪装成自己希望成为的好人的样子，这难道不是他的无间道？\n","collection":"blog","data":{"type":"post","category":"movie"}}]}